{
  "image_filename": "video2.mp4_frame0331.jpg",
  "image_dimensions": {
    "width": 848,
    "height": 480
  },
  "objects": [
    {
      "contour": {
        "x": 356.60540771484375,
        "y": 0.0,
        "w": 177.4093017578125,
        "h": 287.6852111816406
      },
      "obj_name": "person",
      "name_accuracy": 0.9284181594848633
    },
    {
      "contour": {
        "x": 589.6364135742188,
        "y": 0.0,
        "w": 155.3572998046875,
        "h": 316.6333923339844
      },
      "obj_name": "person",
      "name_accuracy": 0.8913422226905823
    },
    {
      "contour": {
        "x": 140.5009307861328,
        "y": 31.728580474853516,
        "w": 53.967132568359375,
        "h": 17.995967864990234
      },
      "obj_name": "car",
      "name_accuracy": 0.6552129983901978
    },
    {
      "contour": {
        "x": 567.74755859375,
        "y": 34.880558013916016,
        "w": 27.10260009765625,
        "h": 12.864326477050781
      },
      "obj_name": "car",
      "name_accuracy": 0.6105604767799377
    },
    {
      "contour": {
        "x": 507.32763671875,
        "y": 26.229618072509766,
        "w": 29.31781005859375,
        "h": 15.539493560791016
      },
      "obj_name": "car",
      "name_accuracy": 0.3877030313014984
    }
  ]
}